{"version":"generated-from-section-csv","source":"user CSV","gpus":[{"key":"nvidia-rtx-pro-6000-se-96gb-96","label":"NVIDIA RTX PRO 6000 SE 96GB","memoryGB":96,"arch":"Blackwell","profiles":[{"name":"DC-8C","gb":8,"maxVms":12,"placementId":"0, 8, 16, 24, 32, 40, 48, 56, 64, 72, 80, 88"},{"name":"DC-12C","gb":12,"maxVms":8,"placementId":"0, 12, 24, 36, 48, 60, 72, 84"},{"name":"DC-16C","gb":16,"maxVms":6,"placementId":"0, 16, 32, 48, 64, 80"},{"name":"DC-24C","gb":24,"maxVms":4,"placementId":"0, 24, 48, 72"},{"name":"DC-32C","gb":32,"maxVms":3,"placementId":"0, 32, 64"},{"name":"DC-48C","gb":48,"maxVms":2,"placementId":"0, 48"},{"name":"DC-96C","gb":96,"maxVms":1,"placementId":"0"}]},{"key":"nvidia-h100-pcie-94gb-h100-nvl-94","label":"NVIDIA H100 PCIe 94GB (H100 NVL)","memoryGB":94,"arch":"Hopper","profiles":[{"name":"H100L-4C","gb":4,"maxVms":16,"placementId":"0, 7, 11, 19, 23, 31, 35, 43, 47, 54, 58, 66, 70, 78, 82, 90"},{"name":"H100L-6C","gb":6,"maxVms":8,"placementId":"0, 17, 23, 41, 47, 64, 70, 88"},{"name":"H100L-11C","gb":11,"maxVms":8,"placementId":"0, 12, 23, 36, 47, 59, 70, 83"},{"name":"H100L-15C","gb":15,"maxVms":4,"placementId":"0, 32, 47, 79"},{"name":"H100L-23C","gb":23,"maxVms":4,"placementId":"0, 24, 47, 71"},{"name":"H100L-47C","gb":47,"maxVms":2,"placementId":"0, 47"},{"name":"H100L-94C","gb":94,"maxVms":1,"placementId":"0"}]},{"key":"nvidia-h100-sxm5-94gb-94","label":"NVIDIA H100 SXM5 94GB","memoryGB":94,"arch":"Hopper","profiles":[{"name":"H100XL-4C","gb":4,"maxVms":16,"placementId":"0, 7, 11, 19, 23, 31, 35, 43, 47, 54, 58, 66, 70, 78, 82, 90"},{"name":"H100XL-6C","gb":6,"maxVms":8,"placementId":"0, 17, 23, 41, 47, 64, 70, 88"},{"name":"H100XL-11C","gb":11,"maxVms":8,"placementId":"0, 12, 23, 36, 47, 59, 70, 83"},{"name":"H100XL-15C","gb":15,"maxVms":4,"placementId":"0, 32, 47, 79"},{"name":"H100XL-23C","gb":23,"maxVms":4,"placementId":"0, 24, 47, 71"},{"name":"H100XL-47C","gb":47,"maxVms":2,"placementId":"0, 47"},{"name":"H100XL-94C","gb":94,"maxVms":1,"placementId":"0"}]},{"key":"nvidia-a100-hgx-80gb-80","label":"NVIDIA A100 HGX 80GB","memoryGB":80,"arch":"Ampere","profiles":[{"name":"A100DX-4C","gb":4,"maxVms":16,"placementId":"0, 6, 10, 16, 20, 26, 30, 36, 40, 46, 50, 56, 60, 66, 70, 76"},{"name":"A100DX-8C","gb":8,"maxVms":8,"placementId":"0, 12, 20, 32, 40, 52, 60, 72"},{"name":"A100DX-10C","gb":10,"maxVms":8,"placementId":"0, 10, 20, 30, 40, 50, 60, 70"},{"name":"A100DX-16C","gb":16,"maxVms":4,"placementId":"0, 24, 40, 64"},{"name":"A100DX-20C","gb":20,"maxVms":4,"placementId":"0, 20, 40, 60"},{"name":"A100DX-40C","gb":40,"maxVms":2,"placementId":"0, 40"},{"name":"A100DX-80C","gb":80,"maxVms":1,"placementId":"0"}]},{"key":"nvidia-a100-pcie-80gb-80","label":"NVIDIA A100 PCIe 80GB","memoryGB":80,"arch":"Ampere","profiles":[{"name":"A100D-4C","gb":4,"maxVms":16,"placementId":"0, 6, 10, 16, 20, 26, 30, 36, 40, 46, 50, 56, 60, 66, 70, 76"},{"name":"A100D-8C","gb":8,"maxVms":8,"placementId":"0, 12, 20, 32, 40, 52, 60, 72"},{"name":"A100D-10C","gb":10,"maxVms":8,"placementId":"0, 10, 20, 30, 40, 50, 60, 70"},{"name":"A100D-16C","gb":16,"maxVms":4,"placementId":"0, 24, 40, 64"},{"name":"A100D-20C","gb":20,"maxVms":4,"placementId":"0, 20, 40, 60"},{"name":"A100D-40C","gb":40,"maxVms":2,"placementId":"0, 40"},{"name":"A100D-80C","gb":80,"maxVms":1,"placementId":"0"}]},{"key":"nvidia-h100-pcie-80gb-80","label":"NVIDIA H100 PCIe 80GB","memoryGB":80,"arch":"Hopper","profiles":[{"name":"H100-4C","gb":4,"maxVms":16,"placementId":"0, 6, 10, 16, 20, 26, 30, 36, 40, 46, 50, 56, 60, 66, 70, 76"},{"name":"H100-5C","gb":5,"maxVms":16,"placementId":"0, 5, 10, 15, 20, 25, 30, 35, 40, 45, 50, 55, 60, 65, 70, 75"},{"name":"H100-8C","gb":8,"maxVms":8,"placementId":"0, 12, 20, 32, 40, 52, 60, 72"},{"name":"H100-10C","gb":10,"maxVms":8,"placementId":"0, 10, 20, 30, 40, 50, 60, 70"},{"name":"H100-16C","gb":16,"maxVms":4,"placementId":"0, 24, 40, 64"},{"name":"H100-20C","gb":20,"maxVms":4,"placementId":"0, 20, 40, 60"},{"name":"H100-40C","gb":40,"maxVms":2,"placementId":"0, 40"},{"name":"H100-80C","gb":80,"maxVms":1,"placementId":"0"}]},{"key":"nvidia-h100-sxm5-80gb-80","label":"NVIDIA H100 SXM5 80GB","memoryGB":80,"arch":"Hopper","profiles":[{"name":"H100XM-4C","gb":4,"maxVms":16,"placementId":"0, 6, 10, 16, 20, 26, 30, 36, 40, 46, 50, 56, 60, 66, 70, 76"},{"name":"H100XM-5C","gb":5,"maxVms":16,"placementId":"0, 5, 10, 15, 20, 25, 30, 35, 40, 45, 50, 55, 60, 65, 70, 75"},{"name":"H100XM-8C","gb":8,"maxVms":8,"placementId":"0, 12, 20, 32, 40, 52, 60, 72"},{"name":"H100XM-10C","gb":10,"maxVms":8,"placementId":"0, 10, 20, 30, 40, 50, 60, 70"},{"name":"H100XM-16C","gb":16,"maxVms":4,"placementId":"0, 24, 40, 64"},{"name":"H100XM-20C","gb":20,"maxVms":4,"placementId":"0, 20, 40, 60"},{"name":"H100XM-40C","gb":40,"maxVms":2,"placementId":"0, 40"},{"name":"H100XM-80C","gb":80,"maxVms":1,"placementId":"0"}]},{"key":"nvidia-l40-48","label":"NVIDIA L40","memoryGB":48,"arch":"Ada Lovelace","profiles":[{"name":"L40-4C","gb":4,"maxVms":8,"placementId":"0, 8, 12, 20, 24, 32, 36, 44"},{"name":"L40-6C","gb":6,"maxVms":8,"placementId":"0, 6, 12, 18, 24, 30, 36, 42"},{"name":"L40-8C","gb":8,"maxVms":4,"placementId":"0, 16, 24, 40"},{"name":"L40-12C","gb":12,"maxVms":4,"placementId":"0, 12, 24, 36"},{"name":"L40-16C","gb":16,"maxVms":2,"placementId":"0, 32"},{"name":"L40-24C","gb":24,"maxVms":2,"placementId":"0, 24"},{"name":"L40-48C","gb":48,"maxVms":1,"placementId":"0"}]},{"key":"nvidia-l40s-48","label":"NVIDIA L40S","memoryGB":48,"arch":"Ada Lovelace","profiles":[{"name":"L40S-4C","gb":4,"maxVms":8,"placementId":"0, 8, 12, 20, 24, 32, 36, 44"},{"name":"L40S-6C","gb":6,"maxVms":8,"placementId":"0, 6, 12, 18, 24, 30, 36, 42"},{"name":"L40S-8C","gb":8,"maxVms":4,"placementId":"0, 16, 24, 40"},{"name":"L40S-12C","gb":12,"maxVms":4,"placementId":"0, 12, 24, 36"},{"name":"L40S-16C","gb":16,"maxVms":2,"placementId":"0, 32"},{"name":"L40S-24C","gb":24,"maxVms":2,"placementId":"0, 24"},{"name":"L40S-48C","gb":48,"maxVms":1,"placementId":"0"}]},{"key":"nvidia-a100-pcie-40gb-40","label":"NVIDIA A100 PCIe 40GB","memoryGB":40,"arch":"Ampere","profiles":[{"name":"A100-4C","gb":4,"maxVms":8,"placementId":"0, 6, 10, 16, 20, 26, 30, 36"},{"name":"A100-5C","gb":5,"maxVms":8,"placementId":"0, 5, 10, 15, 20, 25, 30, 35"},{"name":"A100-8C","gb":8,"maxVms":4,"placementId":"0, 12, 20, 32"},{"name":"A100-10C","gb":10,"maxVms":4,"placementId":"0, 10, 20, 30"},{"name":"A100-20C","gb":20,"maxVms":2,"placementId":"0, 20"},{"name":"A100-40C","gb":40,"maxVms":1,"placementId":"0"}]},{"key":"nvidia-l4-24","label":"NVIDIA L4","memoryGB":24,"arch":"Ada Lovelace","profiles":[{"name":"L4-4C","gb":4,"maxVms":4,"placementId":"0, 8, 12, 20"},{"name":"L4-6C","gb":6,"maxVms":4,"placementId":"0, 6, 12, 18"},{"name":"L4-8C","gb":8,"maxVms":2,"placementId":"0, 16"},{"name":"L4-12C","gb":12,"maxVms":2,"placementId":"0, 12"},{"name":"L4-24C","gb":24,"maxVms":1,"placementId":"0"}]}]}